pandas_pipe/__init__.py
pandas_pipe/pandas_pipe.py
pandas_pipe-0.0.1.dist-info/LICENSE
pandas_pipe-0.0.1.dist-info/WHEEL
pandas_pipe-0.0.1.dist-info/METADATA
pandas_pipe-0.0.1.dist-info/RECORD
