Metadata-Version: 2.1
Name: pandas-pipe
Version: 0.0.1
Summary: routine pandas method chain links wrapped with scikit-lego
Home-page: https://github.com/bdatko/panda_pipe
License: MIT
Author: Benjamin Datko
Requires-Python: >=3.7,<4.0
Classifier: License :: OSI Approved :: MIT License
Classifier: Programming Language :: Python :: 3
Classifier: Programming Language :: Python :: 3.7
Classifier: Programming Language :: Python :: 3.8
Classifier: Programming Language :: Python :: 3.9
Requires-Dist: numpy (>=1.19.2,<2.0.0)
Requires-Dist: pandas (>=1.1.5)
Requires-Dist: scikit-lego (>=0.6.1)
Project-URL: Repository, https://github.com/bdatko/panda_pipe
